sbomdebt/__init__.py
sbomdebt/cli.py
sbomdebt/debt.py
sbomdebt/sbomdebt.py
sbomdebt/version.py
sbomdebt-0.1.0.dist-info/LICENSE
sbomdebt-0.1.0.dist-info/METADATA
sbomdebt-0.1.0.dist-info/WHEEL
sbomdebt-0.1.0.dist-info/entry_points.txt
sbomdebt-0.1.0.dist-info/top_level.txt
sbomdebt-0.1.0.dist-info/RECORD
