Metadata-Version: 2.1
Name: sbomdebt
Version: 0.1.0
Summary: Determine technical debt for a SBOM
Home-page: https://github.com/anthonyharrison/sbomdebt
Author: Anthony Harrison
Author-email: anthony.p.harrison@gmail.com
Maintainer: Anthony Harrison
Maintainer-email: anthony.p.harrison@gmail.com
License: Apache-2.0
Keywords: security,tools,SBOM,DevSecOps,SPDX,CycloneDX,technical-debt
Classifier: Development Status :: 3 - Alpha
Classifier: Intended Audience :: Developers
Classifier: License :: OSI Approved :: Apache Software License
Classifier: Natural Language :: English
Classifier: Operating System :: OS Independent
Classifier: Programming Language :: Python :: 3.8
Classifier: Programming Language :: Python :: 3.9
Classifier: Programming Language :: Python :: 3.10
Classifier: Programming Language :: Python :: 3.11
Classifier: Programming Language :: Python :: 3.12
Classifier: Programming Language :: Python :: Implementation :: CPython
Classifier: Programming Language :: Python :: Implementation :: PyPy
Requires-Python: >=3.8
License-File: LICENSE
Requires-Dist: lib4sbom >=0.7.2
Requires-Dist: lib4package >=0.2.0
Requires-Dist: packageurl-python
Requires-Dist: packaging
